iop_python-0.2.1.dist-info/METADATA
iop_python-0.2.1.dist-info/WHEEL
iop_python/__init__.py
iop_python/iop_python.cpython-312-darwin.so
iop_python-0.2.1.dist-info/RECORD
