Metadata-Version: 2.3
Name: iop-python
Version: 0.2.1
Classifier: Programming Language :: Rust
Classifier: Programming Language :: Python :: Implementation :: CPython
Classifier: Programming Language :: Python :: Implementation :: PyPy
Classifier: Development Status :: 5 - Production/Stable
Keywords: blockchain,hydralegeder,cryptography,bip39,did
Author: Ebuka Offor
Author-email: ebuka2264@yahoo.com
Maintainer-email: Buki <ebuka2264@yahoo.com>,  Odurukwe Stella <odurukwestella5@gmail.com>
Requires-Python: >=3.8
Project-URL: Homepage, https://github.com/BukiOffor/hydra-python-api
Project-URL: Issues, https://github.com/BukiOffor/hydra-python-api/issues
